MANIFEST.in
README.md
RELEASE-VERSION
pavement.py
paver-minilib.zip
setup.py
version.py
blink/__init__.py
blink/Arduino/blink/SConscript
blink/Arduino/blink/blink.ino
blink/firmware/diecimila/blink.hex
blink/firmware/mega2560/blink.hex
blink/firmware/uno/blink.hex
wheeler.blink.egg-info/PKG-INFO
wheeler.blink.egg-info/SOURCES.txt
wheeler.blink.egg-info/dependency_links.txt
wheeler.blink.egg-info/top_level.txt