Metadata-Version: 1.0
Name: wheeler.blink
Version: 0.1.post2.dev193877662
Summary: Example Arduino sketch packaged as Python package.
Home-page: http://github.com/wheeler-microfluidics/blink.git
Author: Christian Fobel
Author-email: christian@fobel.net
License: GPLv2
Platform: UNKNOWN
